AUTHORS
CHANGELOG.txt
DESCRIPTION
LICENSE
MANIFEST.in
README.rst
setup.py
django_rapid_prototyping.egg-info/PKG-INFO
django_rapid_prototyping.egg-info/SOURCES.txt
django_rapid_prototyping.egg-info/dependency_links.txt
django_rapid_prototyping.egg-info/requires.txt
django_rapid_prototyping.egg-info/top_level.txt
rapid_prototyping/__init__.py
rapid_prototyping/admin.py
rapid_prototyping/models.py
rapid_prototyping/urls.py
rapid_prototyping/views.py
rapid_prototyping/context/__init__.py
rapid_prototyping/context/utils.py
rapid_prototyping/static/rapid_prototyping/js/calculate_total.js
rapid_prototyping/templates/rapid_prototyping/costs.html
rapid_prototyping/templates/rapid_prototyping/costs_table_body.html
rapid_prototyping/templates/rapid_prototyping/costs_table_head.html
rapid_prototyping/templates/rapid_prototyping/costs_total.html
rapid_prototyping/templates/rapid_prototyping/sprints.html
rapid_prototyping/templatetags/__init__.py
rapid_prototyping/templatetags/rapid_prototyping_tags.py
rapid_prototyping/tests/__init__.py
rapid_prototyping/tests/context_utils_tests.py
rapid_prototyping/tests/models_tests.py
rapid_prototyping/tests/rapid_prototyping_tags_tests.py
rapid_prototyping/tests/settings.py
rapid_prototyping/tests/test_settings.py
rapid_prototyping/tests/urls.py
rapid_prototyping/tests/views_tests.py
rapid_prototyping/tests/test_app/__init__.py
rapid_prototyping/tests/test_app/models.py
rapid_prototyping/tests/test_app/context/__init__.py
rapid_prototyping/tests/test_app/context/sprints.py
rapid_prototyping/tests/test_app/context/test_costs.py
rapid_prototyping/tests/test_app/templates/400.html
rapid_prototyping/tests/test_app/templates/500.html