Metadata-Version: 1.0
Name: django-rapid-prototyping
Version: 1.0
Summary: A reusable Django app that helps to create prototypes and cost estimations.
